hatasmota/__init__.py
hatasmota/button.py
hatasmota/camera.py
hatasmota/config_validation.py
hatasmota/const.py
hatasmota/device_status.py
hatasmota/discovery.py
hatasmota/entity.py
hatasmota/fan.py
hatasmota/light.py
hatasmota/models.py
hatasmota/mqtt.py
hatasmota/relay.py
hatasmota/sensor.py
hatasmota/shutter.py
hatasmota/status_sensor.py
hatasmota/switch.py
hatasmota/trigger.py
hatasmota/utils.py
hatasmota-0.10.0.dist-info/LICENSE
hatasmota-0.10.0.dist-info/METADATA
hatasmota-0.10.0.dist-info/WHEEL
hatasmota-0.10.0.dist-info/top_level.txt
hatasmota-0.10.0.dist-info/RECORD
